patternity/__init__.py
patternity/collector.py
patternity/pattern.py
patternity-0.1.0.dist-info/LICENSE
patternity-0.1.0.dist-info/METADATA
patternity-0.1.0.dist-info/WHEEL
patternity-0.1.0.dist-info/top_level.txt
patternity-0.1.0.dist-info/RECORD
