Metadata-Version: 2.1
Name: patternity
Version: 0.1.0
Summary: Predict stock prices using a deterministic algorithm inspired by LSTM, focusing on pattern recognition in historical data.
Author: Artyom Vancyan
Author-email: artyom.vancyan2000@gmail.com
License: MIT
Project-URL: Source Code, https://github.com/ArtyomVancyan/patternity/
Keywords: finance,crypto,trading,pattern,prediction,stock,forex,lstm,deterministic
Platform: unix
Platform: linux
Platform: osx
Platform: win32
Classifier: Operating System :: OS Independent
Classifier: Development Status :: 4 - Beta
Classifier: Programming Language :: Python
Classifier: Programming Language :: Python :: 3
Classifier: Programming Language :: Python :: 3.9
Classifier: Programming Language :: Python :: 3.10
Classifier: Programming Language :: Python :: 3.11
Classifier: License :: OSI Approved :: MIT License
Requires-Python: >=3.9
License-File: LICENSE
Requires-Dist: numpy >=1.26.0
Requires-Dist: matplotlib >=3.8.0
Requires-Dist: yfinance >=0.2.33
Requires-Dist: python-binance >=1.0.17
